{"errors":[],"warnings":[],"namedChunkGroups":{"polyfill":{"chunks":[2,0,7],"assets":["webpack-runtime-f08de5e7b05fa46e1543.js","webpack-runtime-f08de5e7b05fa46e1543.js.map","commons-a6b754c88e9accb92f58.js","commons-a6b754c88e9accb92f58.js.map","polyfill-95d38d1bd0e417271a87.js","polyfill-95d38d1bd0e417271a87.js.map"],"children":{},"childAssets":{}},"app":{"chunks":[2,1,6,0,3],"assets":["webpack-runtime-f08de5e7b05fa46e1543.js","webpack-runtime-f08de5e7b05fa46e1543.js.map","styles.f0c26ee0589773d425d7.css","styles-e9d24b1846c7d6eb9685.js","styles-e9d24b1846c7d6eb9685.js.map","framework-f795f4c44743853db08c.js","framework-f795f4c44743853db08c.js.map","commons-a6b754c88e9accb92f58.js","commons-a6b754c88e9accb92f58.js.map","app-e77d6ffed8a2bba38ede.js","app-e77d6ffed8a2bba38ede.js.map"],"children":{},"childAssets":{}},"component---src-pages-404-js":{"chunks":[1,0,4],"assets":["styles.f0c26ee0589773d425d7.css","styles-e9d24b1846c7d6eb9685.js","styles-e9d24b1846c7d6eb9685.js.map","commons-a6b754c88e9accb92f58.js","commons-a6b754c88e9accb92f58.js.map","component---src-pages-404-js-a9723d7aed74b8ce710c.js","component---src-pages-404-js-a9723d7aed74b8ce710c.js.map"],"children":{},"childAssets":{}},"component---src-pages-index-js":{"chunks":[1,0,5],"assets":["styles.f0c26ee0589773d425d7.css","styles-e9d24b1846c7d6eb9685.js","styles-e9d24b1846c7d6eb9685.js.map","commons-a6b754c88e9accb92f58.js","commons-a6b754c88e9accb92f58.js.map","component---src-pages-index-js-289c0e416bcad25363e0.js","component---src-pages-index-js-289c0e416bcad25363e0.js.map"],"children":{},"childAssets":{}}},"assetsByChunkName":{"polyfill":["webpack-runtime-f08de5e7b05fa46e1543.js","commons-a6b754c88e9accb92f58.js","polyfill-95d38d1bd0e417271a87.js"],"app":["webpack-runtime-f08de5e7b05fa46e1543.js","styles.f0c26ee0589773d425d7.css","styles-e9d24b1846c7d6eb9685.js","framework-f795f4c44743853db08c.js","commons-a6b754c88e9accb92f58.js","app-e77d6ffed8a2bba38ede.js"],"component---src-pages-404-js":["styles.f0c26ee0589773d425d7.css","styles-e9d24b1846c7d6eb9685.js","commons-a6b754c88e9accb92f58.js","component---src-pages-404-js-a9723d7aed74b8ce710c.js"],"component---src-pages-index-js":["styles.f0c26ee0589773d425d7.css","styles-e9d24b1846c7d6eb9685.js","commons-a6b754c88e9accb92f58.js","component---src-pages-index-js-289c0e416bcad25363e0.js"]}}